dj_tasks/__init__.py
dj_tasks/admin.py
dj_tasks/apps.py
dj_tasks/models.py
dj_tasks/settings.py
dj_tasks/tasks.py
dj_tasks/utils.py
dj_tasks/management/__init__.py
dj_tasks/management/commands/__init__.py
dj_tasks/management/commands/run_tasks.py
dj_tasks/migrations/0001_initial.py
dj_tasks/migrations/__init__.py
dj_tasks-2.0.0.dist-info/AUTHORS.rst
dj_tasks-2.0.0.dist-info/LICENSE
dj_tasks-2.0.0.dist-info/METADATA
dj_tasks-2.0.0.dist-info/WHEEL
dj_tasks-2.0.0.dist-info/top_level.txt
dj_tasks-2.0.0.dist-info/RECORD
