Metadata-Version: 2.1
Name: dj-tasks
Version: 2.0.0
Summary: A django app to run a collection of tasks in a management command.
Home-page: https://github.com/cfc603/dj-tasks
Author: Trevor Watson
Author-email: wtrevor162@gmail.com
License: MIT
Keywords: dj-tasks
Platform: UNKNOWN
Classifier: Development Status :: 3 - Alpha
Classifier: Framework :: Django :: 3.2
Classifier: Framework :: Django :: 4.0
Classifier: Framework :: Django :: 4.1
Classifier: Intended Audience :: Developers
Classifier: License :: OSI Approved :: BSD License
Classifier: Natural Language :: English
Classifier: Programming Language :: Python :: 3.6
Classifier: Programming Language :: Python :: 3.7
Classifier: Programming Language :: Python :: 3.8
Classifier: Programming Language :: Python :: 3.9
Requires-Dist: django (>=3.0)
Requires-Dist: django-model-utils (>=2.0)
